my_dc09_spt/__init__.py
my_dc09_spt/dc09_spt.py
my_dc09_spt/param.py
my_dc09_spt/utils.py
my_dc09_spt/comm/__init__.py
my_dc09_spt/comm/transpath.py
my_dc09_spt/comm/transpathtcp.py
my_dc09_spt/comm/transpathudp.py
my_dc09_spt/example/__init__.py
my_dc09_spt/example/testdailler.py
my_dc09_spt/example/testsendmsg.py
my_dc09_spt/msg/__init__.py
my_dc09_spt/msg/dc03_msg.py
my_dc09_spt/msg/dc05_msg.py
my_dc09_spt/msg/dc09_msg.py
my_dc09_spt-0.2.2.dist-info/LICENSE
my_dc09_spt-0.2.2.dist-info/METADATA
my_dc09_spt-0.2.2.dist-info/WHEEL
my_dc09_spt-0.2.2.dist-info/top_level.txt
my_dc09_spt-0.2.2.dist-info/RECORD
