Metadata-Version: 2.1
Name: my_dc09_spt
Version: 0.2.2
Summary: A dialler implementation using the SIA-DC09 protocol
Home-page: https://github.com/jvanovost/dc09_spt
Author: Jacq. van Ovost
Author-email: jacq.van.ovost@gmail.com
Keywords: DC09,SIA DC09,SPT,Alarm transmitter
Classifier: Programming Language :: Python :: 3
Classifier: License :: OSI Approved :: Apache Software License
Classifier: Operating System :: OS Independent
Requires-Python: >=3.6
License-File: LICENSE
Requires-Dist: cryptography >=3.1
